webgo/__init__.py
webgo/config.py
webgo/exceptions.py
webgo/handler.py
webgo/orm.py
webgo/template.py
webgo/tools.py
webgo/webgoapp.py
webgo/wsgiserver.py
webgo-0.14.0.dist-info/LICENSE
webgo-0.14.0.dist-info/METADATA
webgo-0.14.0.dist-info/WHEEL
webgo-0.14.0.dist-info/entry_points.txt
webgo-0.14.0.dist-info/top_level.txt
webgo-0.14.0.dist-info/RECORD
