Metadata-Version: 2.1
Name: webgo
Version: 0.14.0
Summary: A micro web framework
Home-page: https://github.com/1xuan/webgo
Author: yixuan
Author-email: yixuan.coder@gmail.com
License: MIT
Platform: UNKNOWN
Classifier: Programming Language :: Python :: 3
Classifier: License :: OSI Approved :: MIT License
Classifier: Operating System :: OS Independent
Requires-Python: >=3.6
Requires-Dist: Jinja2
Requires-Dist: MarkupSafe
Requires-Dist: WebOb
